azure/graphrbac/__init__.py
azure/graphrbac/graph_rbac_management_client.py
azure/graphrbac/version.py
azure/graphrbac/models/__init__.py
azure/graphrbac/models/ad_group.py
azure/graphrbac/models/ad_group_paged.py
azure/graphrbac/models/ad_group_py3.py
azure/graphrbac/models/add_owner_parameters.py
azure/graphrbac/models/add_owner_parameters_py3.py
azure/graphrbac/models/app_role.py
azure/graphrbac/models/app_role_py3.py
azure/graphrbac/models/application.py
azure/graphrbac/models/application_base.py
azure/graphrbac/models/application_base_py3.py
azure/graphrbac/models/application_create_parameters.py
azure/graphrbac/models/application_create_parameters_py3.py
azure/graphrbac/models/application_paged.py
azure/graphrbac/models/application_py3.py
azure/graphrbac/models/application_update_parameters.py
azure/graphrbac/models/application_update_parameters_py3.py
azure/graphrbac/models/check_group_membership_parameters.py
azure/graphrbac/models/check_group_membership_parameters_py3.py
azure/graphrbac/models/check_group_membership_result.py
azure/graphrbac/models/check_group_membership_result_py3.py
azure/graphrbac/models/directory_object.py
azure/graphrbac/models/directory_object_paged.py
azure/graphrbac/models/directory_object_py3.py
azure/graphrbac/models/domain.py
azure/graphrbac/models/domain_paged.py
azure/graphrbac/models/domain_py3.py
azure/graphrbac/models/get_objects_parameters.py
azure/graphrbac/models/get_objects_parameters_py3.py
azure/graphrbac/models/graph_error.py
azure/graphrbac/models/graph_error_py3.py
azure/graphrbac/models/graph_rbac_management_client_enums.py
azure/graphrbac/models/group_add_member_parameters.py
azure/graphrbac/models/group_add_member_parameters_py3.py
azure/graphrbac/models/group_create_parameters.py
azure/graphrbac/models/group_create_parameters_py3.py
azure/graphrbac/models/group_get_member_groups_parameters.py
azure/graphrbac/models/group_get_member_groups_parameters_py3.py
azure/graphrbac/models/informational_url.py
azure_graphrbac-0.61.0.dist-info/METADATA
azure_graphrbac-0.61.0.dist-info/WHEEL
azure_graphrbac-0.61.0.dist-info/top_level.txt
azure_graphrbac-0.61.0.dist-info/RECORD
